Metadata-Version: 1.1
Name: haythambasecal
Version: 0.0.1
Summary: a basic calculator
Home-page: UNKNOWN
Author: haytham omar
Author-email: haytham.omar@kedgebs.com
License: MIT
Keywords: calculator
Platform: UNKNOWN
Classifier: Development Status :: 5 - Production/Stable
Classifier: Operating System :: Microsoft :: Windows :: Windows 10
Classifier: License :: OSI Approved :: MIT License
Classifier:  Programming Language :: Python :: 3
